basic_utility/__init__.py
basic_utility/_nbdev.py
basic_utility/core.py
basic_utility-0.0.1.dist-info/LICENSE
basic_utility-0.0.1.dist-info/METADATA
basic_utility-0.0.1.dist-info/WHEEL
basic_utility-0.0.1.dist-info/entry_points.txt
basic_utility-0.0.1.dist-info/top_level.txt
basic_utility-0.0.1.dist-info/RECORD
